Metadata-Version: 1.1
Name: django-newsletter-gardentronic
Version: 0.9.0.post5
Summary: Django app for managing multiple mass-mailing lists with both plaintext as well as HTML templates (and pluggable WYSIWYG editors for messages), images and a smart queueing system all right from the admin interface.
Home-page: https://github.com/dokterbob/django-newsletter/
Author: Mathijs de Bruin
Author-email: mathijs@mathijsfietst.nl
License: UNKNOWN
Platform: UNKNOWN
Classifier: Development Status :: 6 - Mature
Classifier: Environment :: Web Environment
Classifier: Framework :: Django
Classifier: Intended Audience :: Developers
Classifier: License :: OSI Approved :: GNU Affero General Public License v3
Classifier: Operating System :: OS Independent
Classifier: Programming Language :: Python
Classifier: Programming Language :: Python :: 3.4
Classifier: Programming Language :: Python :: 3.5
Classifier: Programming Language :: Python :: 3.6
Classifier: Programming Language :: Python :: 3.7
Classifier: Programming Language :: Python :: 3.8
Classifier: Topic :: Utilities
